{
    "kanji": "\u5e4c",
    "hexadecimal": "05e4c",
    "jpdb_keyword": "",
    "rtk_keyword": "",
    "kklc_keyword": "",
    "frequency": 0,
    "jouyou_level": "",
    "JLPT": "",
    "onyomi": [],
    "kunyomi": [],
    "components": [],
    "strokes": 0,
    "svg": "b'<?xml version=\"1.0\" encoding=\"UTF-8\"?>\\n<!--\\nCopyright (C) 2009/2010/2011 Ulrich Apel.\\nThis work is distributed under the conditions of the Creative Commons\\nAttribution-Share Alike 3.0 Licence. This means you are free:\\n* to Share - to copy, distribute and transmit the work\\n* to Remix - to adapt the work\\n\\nUnder the following conditions:\\n* Attribution. You must attribute the work by stating your use of KanjiVG in\\n  your own copyright header and linking to KanjiVG\\'s website\\n  (http://kanjivg.tagaini.net)\\n* Share Alike. If you alter, transform, or build upon this work, you may\\n  distribute the resulting work only under the same or similar license to this\\n  one.\\n\\nSee http://creativecommons.org/licenses/by-sa/3.0/ for more details.\\n-->\\n<!DOCTYPE svg PUBLIC \"-//W3C//DTD SVG 1.0//EN\" \"http://www.w3.org/TR/2001/REC-SVG-20010904/DTD/svg10.dtd\" [\\n<!ATTLIST g\\nxmlns:kvg CDATA #FIXED \"http://kanjivg.tagaini.net\"\\nkvg:element CDATA #IMPLIED\\nkvg:variant CDATA #IMPLIED\\nkvg:partial CDATA #IMPLIED\\nkvg:original CDATA #IMPLIED\\nkvg:part CDATA #IMPLIED\\nkvg:number CDATA #IMPLIED\\nkvg:tradForm CDATA #IMPLIED\\nkvg:radicalForm CDATA #IMPLIED\\nkvg:position CDATA #IMPLIED\\nkvg:radical CDATA #IMPLIED\\nkvg:phon CDATA #IMPLIED >\\n<!ATTLIST path\\nxmlns:kvg CDATA #FIXED \"http://kanjivg.tagaini.net\"\\nkvg:type CDATA #IMPLIED >\\n]>\\n<svg xmlns=\"http://www.w3.org/2000/svg\" width=\"109\" height=\"109\" viewBox=\"0 0 109 109\">\\n<g id=\"kvg:StrokePaths_05e4c\" style=\"fill:none;stroke:#000000;stroke-width:3;stroke-linecap:round;stroke-linejoin:round;\">\\n<g id=\"kvg:05e4c\" kvg:element=\"\\xe5\\xb9\\x8c\">\\n\\t<g id=\"kvg:05e4c-g1\" kvg:element=\"\\xe5\\xb7\\xbe\" kvg:position=\"left\" kvg:radical=\"general\">\\n\\t\\t<path id=\"kvg:05e4c-s1\" kvg:type=\"\\xe3\\x87\\x91\" d=\"M12.49,35.31c0.43,0.39,1.33,2.88,1.42,3.65c0.34,3.04-0.56,28.67-0.64,33.48\"/>\\n\\t\\t<path id=\"kvg:05e4c-s2\" kvg:type=\"\\xe3\\x87\\x86a\" d=\"M13.79,37.25c2.47-0.27,22.65-3.91,24.49-4.07c2.16-0.19,3.52,1.34,3.55,3.07C42,45,41.74,55.59,40.47,64.13c-0.91,6.14-4.25,1.85-5.29-0.27\"/>\\n\\t\\t<path id=\"kvg:05e4c-s3\" kvg:type=\"\\xe3\\x87\\x91\" d=\"M24.5,11.63c0.61,0.42,1.5,2.12,1.51,4.03c0.01,0.86-0.08,77.66-0.2,82.97\"/>\\n\\t</g>\\n\\t<g id=\"kvg:05e4c-g2\" kvg:element=\"\\xe6\\x99\\x83\" kvg:position=\"right\">\\n\\t\\t<g id=\"kvg:05e4c-g3\" kvg:element=\"\\xe6\\x97\\xa5\" kvg:position=\"top\">\\n\\t\\t\\t<path id=\"kvg:05e4c-s4\" kvg:type=\"\\xe3\\x87\\x91\" d=\"M48.69,13.94c0.39,0.44,0.4,0.75,0.62,1.31c1.77,4.6,3.03,14.29,4.12,22.87\"/>\\n\\t\\t\\t<path id=\"kvg:05e4c-s5\" kvg:type=\"\\xe3\\x87\\x95a\" d=\"M50.35,15.39c9.43-0.96,26.66-2.56,33.7-3.36c2.59-0.3,3.11,1.69,2.98,2.74c-0.49,3.84-1.96,13.82-3.96,20.24\"/>\\n\\t\\t\\t<path id=\"kvg:05e4c-s6\" kvg:type=\"\\xe3\\x87\\x90a\" d=\"M53.11,25.71c3.07-0.37,28.06-3.09,30.59-3.25\"/>\\n\\t\\t\\t<path id=\"kvg:05e4c-s7\" kvg:type=\"\\xe3\\x87\\x90a\" d=\"M54.11,36.43c8.73-1.05,19.56-2.09,28.93-2.75\"/>\\n\\t\\t</g>\\n\\t\\t<g id=\"kvg:05e4c-g4\" kvg:element=\"\\xe5\\x85\\x89\" kvg:position=\"bottom\">\\n\\t\\t\\t<g id=\"kvg:05e4c-g5\" kvg:element=\"\\xe2\\xba\\x8c\" kvg:variant=\"true\" kvg:original=\"\\xe5\\xb0\\x8f\" kvg:position=\"top\">\\n\\t\\t\\t\\t<path id=\"kvg:05e4c-s8\" kvg:type=\"\\xe3\\x87\\x91\" d=\"M67.35,42.01c0.07,0.23,0.94,1.23,1,2.73c0.32,7.2-0.2,15.97-0.2,18.42\"/>\\n\\t\\t\\t\\t<path id=\"kvg:05e4c-s9\" kvg:type=\"\\xe3\\x87\\x94\" d=\"M50.07,47.59c2.36,1.92,6.1,7.9,6.69,10.9\"/>\\n\\t\\t\\t\\t<path id=\"kvg:05e4c-s10\" kvg:type=\"\\xe3\\x87\\x92\" d=\"M85.22,43.44c0.02,0.3,0.04,0.77-0.04,1.2c-0.51,2.52-3.42,8.06-7.41,11.45\"/>\\n\\t\\t\\t</g>\\n\\t\\t\\t<g id=\"kvg:05e4c-g6\" kvg:element=\"\\xe5\\x85\\x80\" kvg:position=\"bottom\">\\n\\t\\t\\t\\t<g id=\"kvg:05e4c-g7\" kvg:element=\"\\xe4\\xb8\\x80\">\\n\\t\\t\\t\\t\\t<path id=\"kvg:05e4c-s11\" kvg:type=\"\\xe3\\x87\\x90\" d=\"M46.96,65.66c1.13,0.49,3.2,0.63,4.32,0.49c11.22-1.4,26.35-4.61,39.52-4.71c1.88-0.02,3,0.24,3.94,0.48\"/>\\n\\t\\t\\t\\t</g>\\n\\t\\t\\t\\t<g id=\"kvg:05e4c-g8\" kvg:element=\"\\xe5\\x84\\xbf\" kvg:original=\"\\xe5\\x85\\xab\">\\n\\t\\t\\t\\t\\t<g id=\"kvg:05e4c-g9\" kvg:element=\"\\xe4\\xb8\\xbf\">\\n\\t\\t\\t\\t\\t\\t<path id=\"kvg:05e4c-s12\" kvg:type=\"\\xe3\\x87\\x92\" d=\"M60.84,69.56c0.05,0.66,0.16,1.71-0.11,2.65c-2.28,7.96-9.05,20.4-19.95,25.34\"/>\\n\\t\\t\\t\\t\\t</g>\\n\\t\\t\\t\\t\\t<path id=\"kvg:05e4c-s13\" kvg:type=\"\\xe3\\x87\\x9f\" d=\"M73.92,66.57c0.5,0.9,0.9,1.97,0.93,3.36c0.08,3.6-0.24,12.25-0.38,17.82c-0.21,8.25,3.7,9.46,10.74,9.46s11.56-0.96,11.56-6.67\"/>\\n\\t\\t\\t\\t</g>\\n\\t\\t\\t</g>\\n\\t\\t</g>\\n\\t</g>\\n</g>\\n</g>\\n<g id=\"kvg:StrokeNumbers_05e4c\" style=\"font-size:8;fill:#808080\">\\n\\t<text transform=\"matrix(1 0 0 1 6.50 42.50)\">1</text>\\n\\t<text transform=\"matrix(1 0 0 1 15.75 33.50)\">2</text>\\n\\t<text transform=\"matrix(1 0 0 1 15.75 12.48)\">3</text>\\n\\t<text transform=\"matrix(1 0 0 1 42.50 21.50)\">4</text>\\n\\t<text transform=\"matrix(1 0 0 1 53.50 11.50)\">5</text>\\n\\t<text transform=\"matrix(1 0 0 1 55.50 22.10)\">6</text>\\n\\t<text transform=\"matrix(1 0 0 1 56.50 33.28)\">7</text>\\n\\t<text transform=\"matrix(1 0 0 1 57.50 45.50)\">8</text>\\n\\t<text transform=\"matrix(1 0 0 1 45.50 53.38)\">9</text>\\n\\t<text transform=\"matrix(1 0 0 1 73.50 45.80)\">10</text>\\n\\t<text transform=\"matrix(1 0 0 1 44.50 62.50)\">11</text>\\n\\t<text transform=\"matrix(1 0 0 1 49.50 75.50)\">12</text>\\n\\t<text transform=\"matrix(1 0 0 1 64.50 78.50)\">13</text>\\n</g>\\n</svg>\\n'"
}