{
    "kanji": "\u6d6e",
    "hexadecimal": "06d6e",
    "jpdb_keyword": "",
    "rtk_keyword": "",
    "kklc_keyword": "",
    "frequency": 0,
    "jouyou_level": "",
    "JLPT": "",
    "onyomi": [],
    "kunyomi": [],
    "components": [],
    "strokes": 0,
    "svg": "b'<?xml version=\"1.0\" encoding=\"UTF-8\"?>\\n<!--\\nCopyright (C) 2009/2010/2011 Ulrich Apel.\\nThis work is distributed under the conditions of the Creative Commons\\nAttribution-Share Alike 3.0 Licence. This means you are free:\\n* to Share - to copy, distribute and transmit the work\\n* to Remix - to adapt the work\\n\\nUnder the following conditions:\\n* Attribution. You must attribute the work by stating your use of KanjiVG in\\n  your own copyright header and linking to KanjiVG\\'s website\\n  (http://kanjivg.tagaini.net)\\n* Share Alike. If you alter, transform, or build upon this work, you may\\n  distribute the resulting work only under the same or similar license to this\\n  one.\\n\\nSee http://creativecommons.org/licenses/by-sa/3.0/ for more details.\\n-->\\n<!DOCTYPE svg PUBLIC \"-//W3C//DTD SVG 1.0//EN\" \"http://www.w3.org/TR/2001/REC-SVG-20010904/DTD/svg10.dtd\" [\\n<!ATTLIST g\\nxmlns:kvg CDATA #FIXED \"http://kanjivg.tagaini.net\"\\nkvg:element CDATA #IMPLIED\\nkvg:variant CDATA #IMPLIED\\nkvg:partial CDATA #IMPLIED\\nkvg:original CDATA #IMPLIED\\nkvg:part CDATA #IMPLIED\\nkvg:number CDATA #IMPLIED\\nkvg:tradForm CDATA #IMPLIED\\nkvg:radicalForm CDATA #IMPLIED\\nkvg:position CDATA #IMPLIED\\nkvg:radical CDATA #IMPLIED\\nkvg:phon CDATA #IMPLIED >\\n<!ATTLIST path\\nxmlns:kvg CDATA #FIXED \"http://kanjivg.tagaini.net\"\\nkvg:type CDATA #IMPLIED >\\n]>\\n<svg xmlns=\"http://www.w3.org/2000/svg\" width=\"109\" height=\"109\" viewBox=\"0 0 109 109\">\\n<g id=\"kvg:StrokePaths_06d6e\" style=\"fill:none;stroke:#000000;stroke-width:3;stroke-linecap:round;stroke-linejoin:round;\">\\n<g id=\"kvg:06d6e\" kvg:element=\"\\xe6\\xb5\\xae\">\\n\\t<g id=\"kvg:06d6e-g1\" kvg:element=\"\\xe6\\xb0\\xb5\" kvg:variant=\"true\" kvg:original=\"\\xe6\\xb0\\xb4\" kvg:position=\"left\" kvg:radical=\"general\">\\n\\t\\t<path id=\"kvg:06d6e-s1\" kvg:type=\"\\xe3\\x87\\x94\" d=\"M22.12,17.88c3.93,1.45,10.14,5.96,11.12,8.22\"/>\\n\\t\\t<path id=\"kvg:06d6e-s2\" kvg:type=\"\\xe3\\x87\\x94\" d=\"M16,40.12c4.15,1.26,10.71,5.17,11.75,7.12\"/>\\n\\t\\t<path id=\"kvg:06d6e-s3\" kvg:type=\"\\xe3\\x87\\x80\" d=\"M12.72,88.81c1.4,0.19,2.25-0.04,3.14-1.32C19,82.92,24.12,73.75,27.75,67.5\"/>\\n\\t</g>\\n\\t<g id=\"kvg:06d6e-g2\" kvg:element=\"\\xe5\\xad\\x9a\" kvg:variant=\"true\" kvg:position=\"right\" kvg:phon=\"\\xe5\\xad\\x9a\">\\n\\t\\t<g id=\"kvg:06d6e-g3\" kvg:element=\"\\xe2\\xba\\xa4\" kvg:variant=\"true\" kvg:original=\"\\xe7\\x88\\xaa\" kvg:position=\"top\">\\n\\t\\t\\t<path id=\"kvg:06d6e-s4\" kvg:type=\"\\xe3\\x87\\x92\" d=\"M73.52,12.04c-0.4,1.21-1.18,1.7-1.9,2.08c-5.12,2.64-10.74,4.76-22.51,7.86\"/>\\n\\t\\t\\t<path id=\"kvg:06d6e-s5\" kvg:type=\"\\xe3\\x87\\x94\" d=\"M44.02,29.99c2.84,1.73,6.59,6.64,7.3,9.34\"/>\\n\\t\\t\\t<path id=\"kvg:06d6e-s6\" kvg:type=\"\\xe3\\x87\\x94\" d=\"M59.19,25.76c2.36,1.74,5.36,6.64,5.95,9.34\"/>\\n\\t\\t\\t<path id=\"kvg:06d6e-s7\" kvg:type=\"\\xe3\\x87\\x92\" d=\"M87.02,21.09c0.12,0.91-0.3,1.76-0.76,2.55c-2.38,3.36-5.86,7.47-12.07,12.69\"/>\\n\\t\\t</g>\\n\\t\\t<g id=\"kvg:06d6e-g4\" kvg:element=\"\\xe5\\xad\\x90\" kvg:position=\"bottom\">\\n\\t\\t\\t<path id=\"kvg:06d6e-s8\" kvg:type=\"\\xe3\\x87\\x96\" d=\"M45.73,46.87c2.47,0.62,5.05,0.6,7.55,0.14c7.32-1.36,19.85-3.88,27.28-5.26c1.78-0.33,2.82,1.48,0.86,2.84c-3.29,2.28-13.13,9.24-17.72,12.07\"/>\\n\\t\\t\\t<path id=\"kvg:06d6e-s9\" kvg:type=\"\\xe3\\x87\\x81\" d=\"M62.97,56.91c8.66,9.59,10.25,25.98,7.46,33.41c-2.32,6.19-7.26,8.14-12.14,1.69\"/>\\n\\t\\t\\t<path id=\"kvg:06d6e-s10\" kvg:type=\"\\xe3\\x87\\x90\" d=\"M36.5,69.89c2.5,0.73,5.83,0.61,8.12,0.24c11.75-1.88,32.5-4.3,44.12-5.21c3.01-0.24,6.6-0.08,9.5,0.84\"/>\\n\\t\\t</g>\\n\\t</g>\\n</g>\\n</g>\\n<g id=\"kvg:StrokeNumbers_06d6e\" style=\"font-size:8;fill:#808080\">\\n\\t<text transform=\"matrix(1 0 0 1 15.75 18.13)\">1</text>\\n\\t<text transform=\"matrix(1 0 0 1 8.50 41.50)\">2</text>\\n\\t<text transform=\"matrix(1 0 0 1 4.50 92.98)\">3</text>\\n\\t<text transform=\"matrix(1 0 0 1 63.50 11.50)\">4</text>\\n\\t<text transform=\"matrix(1 0 0 1 36.50 33.50)\">5</text>\\n\\t<text transform=\"matrix(1 0 0 1 51.50 29.50)\">6</text>\\n\\t<text transform=\"matrix(1 0 0 1 78.25 23.50)\">7</text>\\n\\t<text transform=\"matrix(1 0 0 1 38.25 47.50)\">8</text>\\n\\t<text transform=\"matrix(1 0 0 1 56.25 61.50)\">9</text>\\n\\t<text transform=\"matrix(1 0 0 1 34.50 67.50)\">10</text>\\n</g>\\n</svg>\\n'"
}