{
    "kanji": "\u727e",
    "hexadecimal": "0727e",
    "jpdb_keyword": "",
    "rtk_keyword": "",
    "kklc_keyword": "",
    "frequency": 0,
    "jouyou_level": "",
    "JLPT": "",
    "onyomi": [],
    "kunyomi": [],
    "components": [],
    "strokes": 0,
    "svg": "b'<?xml version=\"1.0\" encoding=\"UTF-8\"?>\\n<!--\\nCopyright (C) 2009/2010/2011 Ulrich Apel.\\nThis work is distributed under the conditions of the Creative Commons\\nAttribution-Share Alike 3.0 Licence. This means you are free:\\n* to Share - to copy, distribute and transmit the work\\n* to Remix - to adapt the work\\n\\nUnder the following conditions:\\n* Attribution. You must attribute the work by stating your use of KanjiVG in\\n  your own copyright header and linking to KanjiVG\\'s website\\n  (http://kanjivg.tagaini.net)\\n* Share Alike. If you alter, transform, or build upon this work, you may\\n  distribute the resulting work only under the same or similar license to this\\n  one.\\n\\nSee http://creativecommons.org/licenses/by-sa/3.0/ for more details.\\n-->\\n<!DOCTYPE svg PUBLIC \"-//W3C//DTD SVG 1.0//EN\" \"http://www.w3.org/TR/2001/REC-SVG-20010904/DTD/svg10.dtd\" [\\n<!ATTLIST g\\nxmlns:kvg CDATA #FIXED \"http://kanjivg.tagaini.net\"\\nkvg:element CDATA #IMPLIED\\nkvg:variant CDATA #IMPLIED\\nkvg:partial CDATA #IMPLIED\\nkvg:original CDATA #IMPLIED\\nkvg:part CDATA #IMPLIED\\nkvg:number CDATA #IMPLIED\\nkvg:tradForm CDATA #IMPLIED\\nkvg:radicalForm CDATA #IMPLIED\\nkvg:position CDATA #IMPLIED\\nkvg:radical CDATA #IMPLIED\\nkvg:phon CDATA #IMPLIED >\\n<!ATTLIST path\\nxmlns:kvg CDATA #FIXED \"http://kanjivg.tagaini.net\"\\nkvg:type CDATA #IMPLIED >\\n]>\\n<svg xmlns=\"http://www.w3.org/2000/svg\" width=\"109\" height=\"109\" viewBox=\"0 0 109 109\">\\n<g id=\"kvg:StrokePaths_0727e\" style=\"fill:none;stroke:#000000;stroke-width:3;stroke-linecap:round;stroke-linejoin:round;\">\\n<g id=\"kvg:0727e\" kvg:element=\"\\xe7\\x89\\xbe\">\\n\\t<g id=\"kvg:0727e-g1\" kvg:element=\"\\xe7\\x89\\x9b\" kvg:variant=\"true\" kvg:position=\"left\" kvg:radical=\"general\">\\n\\t\\t<path id=\"kvg:0727e-s1\" kvg:type=\"\\xe3\\x87\\x92\" d=\"M21.28,23.14c0.03,0.69,0.06,1.78-0.05,2.77c-0.65,5.85-4.35,18.69-9.42,26.55\"/>\\n\\t\\t<path id=\"kvg:0727e-s2\" kvg:type=\"\\xe3\\x87\\x90\" d=\"M20.75,38.75c0.87-0.05,1.81,0.37,2.78,0.24c5.47-0.74,14.86-2.74,15.97-2.74c1.25,0,2.5,0,3.75,0.25\"/>\\n\\t\\t<path id=\"kvg:0727e-s3\" kvg:type=\"\\xe3\\x87\\x91\" d=\"M30.37,11.75c1.09,0.5,1.74,2.25,1.96,3.25c0.22,1,0,76.75-0.22,83\"/>\\n\\t\\t<path id=\"kvg:0727e-s4\" kvg:type=\"\\xe3\\x87\\x80\" d=\"M13,66.9c1.73,1.12,3.18,1.1,4.91,0.14c1.02-0.57,19.25-11.81,23.59-14.54\"/>\\n\\t</g>\\n\\t<g id=\"kvg:0727e-g2\" kvg:element=\"\\xe5\\x90\\xbe\" kvg:position=\"right\">\\n\\t\\t<g id=\"kvg:0727e-g3\" kvg:element=\"\\xe4\\xba\\x94\" kvg:position=\"top\">\\n\\t\\t\\t<g id=\"kvg:0727e-g4\" kvg:element=\"\\xe4\\xba\\x8c\" kvg:part=\"1\">\\n\\t\\t\\t\\t<path id=\"kvg:0727e-s5\" kvg:type=\"\\xe3\\x87\\x90\" d=\"M49.54,19.23c1.03,0.35,2.92,0.31,3.96,0.2c8.62-0.84,21.28-2.76,34.58-3.18c1.73-0.05,2.76,0.05,3.62,0.21\"/>\\n\\t\\t\\t</g>\\n\\t\\t\\t<path id=\"kvg:0727e-s6\" kvg:type=\"\\xe3\\x87\\x91a\" d=\"M65.66,21.25c0.43,0.38,1.12,1.75,0.96,2.68c-1.52,8.93-5.29,25.09-6.88,30.74\"/>\\n\\t\\t\\t<path id=\"kvg:0727e-s7\" kvg:type=\"\\xe3\\x87\\x95c\" d=\"M50.93,35.21c0.79,0.4,3.38,0.54,4.03,0.46c9.3-1.17,20.3-2.17,26.81-2.9c1.5-0.17,3.21,1.23,3.21,2.93c0,2.91-1.77,11.17-2.98,17.55\"/>\\n\\t\\t\\t<g id=\"kvg:0727e-g5\" kvg:element=\"\\xe4\\xba\\x8c\" kvg:part=\"2\">\\n\\t\\t\\t\\t<path id=\"kvg:0727e-s8\" kvg:type=\"\\xe3\\x87\\x90\" d=\"M45.33,55.91c1.21,0.22,4.23,0.19,5.43,0.07C60.75,55,79,53.25,93.69,52.83c2.02-0.06,4.02-0.02,5.03,0.08\"/>\\n\\t\\t\\t</g>\\n\\t\\t</g>\\n\\t\\t<g id=\"kvg:0727e-g6\" kvg:element=\"\\xe5\\x8f\\xa3\" kvg:position=\"bottom\">\\n\\t\\t\\t<path id=\"kvg:0727e-s9\" kvg:type=\"\\xe3\\x87\\x91\" d=\"M50.08,66.13c0.49,0.62,0.99,1.14,1.21,1.92c1.7,6.15,3.73,16.15,4.89,27.2\"/>\\n\\t\\t\\t<path id=\"kvg:0727e-s10\" kvg:type=\"\\xe3\\x87\\x95b\" d=\"M51.86,68.79C62.75,67,79,65.58,84.84,65.02c2.14-0.21,3.33,1.2,3.11,2.43c-1.21,6.8-2.46,13.55-3.63,22.96\"/>\\n\\t\\t\\t<path id=\"kvg:0727e-s11\" kvg:type=\"\\xe3\\x87\\x90b\" d=\"M56.2,92.74C63.07,92.11,77,91,86.96,90.53\"/>\\n\\t\\t</g>\\n\\t</g>\\n</g>\\n</g>\\n<g id=\"kvg:StrokeNumbers_0727e\" style=\"font-size:8;fill:#808080\">\\n\\t<text transform=\"matrix(1 0 0 1 13.50 22.50)\">1</text>\\n\\t<text transform=\"matrix(1 0 0 1 23.66 35.35)\">2</text>\\n\\t<text transform=\"matrix(1 0 0 1 21.50 12.50)\">3</text>\\n\\t<text transform=\"matrix(1 0 0 1 5.54 70.50)\">4</text>\\n\\t<text transform=\"matrix(1 0 0 1 46.50 15.50)\">5</text>\\n\\t<text transform=\"matrix(1 0 0 1 58.50 27.50)\">6</text>\\n\\t<text transform=\"matrix(1 0 0 1 48.50 32.50)\">7</text>\\n\\t<text transform=\"matrix(1 0 0 1 46.50 52.50)\">8</text>\\n\\t<text transform=\"matrix(1 0 0 1 43.25 72.50)\">9</text>\\n\\t<text transform=\"matrix(1 0 0 1 52.50 64.50)\">10</text>\\n\\t<text transform=\"matrix(1 0 0 1 58.50 89.50)\">11</text>\\n</g>\\n</svg>\\n'"
}