{
    "kanji": "\u7c13",
    "hexadecimal": "07c13",
    "jpdb_keyword": "",
    "rtk_keyword": "",
    "kklc_keyword": "",
    "frequency": 0,
    "jouyou_level": "",
    "JLPT": "",
    "onyomi": [],
    "kunyomi": [],
    "components": [],
    "strokes": 0,
    "svg": "<?xml version=\"1.0\" encoding=\"UTF-8\"?>\n<!--\nCopyright (C) 2009/2010/2011 Ulrich Apel.\nThis work is distributed under the conditions of the Creative Commons\nAttribution-Share Alike 3.0 Licence. This means you are free:\n* to Share - to copy, distribute and transmit the work\n* to Remix - to adapt the work\n\nUnder the following conditions:\n* Attribution. You must attribute the work by stating your use of KanjiVG in\n  your own copyright header and linking to KanjiVG's website\n  (http://kanjivg.tagaini.net)\n* Share Alike. If you alter, transform, or build upon this work, you may\n  distribute the resulting work only under the same or similar license to this\n  one.\n\nSee http://creativecommons.org/licenses/by-sa/3.0/ for more details.\n-->\n<!DOCTYPE svg PUBLIC \"-//W3C//DTD SVG 1.0//EN\" \"http://www.w3.org/TR/2001/REC-SVG-20010904/DTD/svg10.dtd\" [\n<!ATTLIST g\nxmlns:kvg CDATA #FIXED \"http://kanjivg.tagaini.net\"\nkvg:element CDATA #IMPLIED\nkvg:variant CDATA #IMPLIED\nkvg:partial CDATA #IMPLIED\nkvg:original CDATA #IMPLIED\nkvg:part CDATA #IMPLIED\nkvg:number CDATA #IMPLIED\nkvg:tradForm CDATA #IMPLIED\nkvg:radicalForm CDATA #IMPLIED\nkvg:position CDATA #IMPLIED\nkvg:radical CDATA #IMPLIED\nkvg:phon CDATA #IMPLIED >\n<!ATTLIST path\nxmlns:kvg CDATA #FIXED \"http://kanjivg.tagaini.net\"\nkvg:type CDATA #IMPLIED >\n]>\n<svg xmlns=\"http://www.w3.org/2000/svg\" width=\"109\" height=\"109\" viewBox=\"0 0 109 109\">\n<g id=\"kvg:StrokePaths_07c13\" style=\"fill:none;stroke:#000000;stroke-width:3;stroke-linecap:round;stroke-linejoin:round;\">\n<g id=\"kvg:07c13\" kvg:element=\"\u7c13\">\n\t<g id=\"kvg:07c13-g1\" kvg:element=\"\u7af9\" kvg:variant=\"true\" kvg:position=\"top\" kvg:radical=\"general\">\n\t\t<g id=\"kvg:07c13-g2\" kvg:position=\"left\">\n\t\t\t<path id=\"kvg:07c13-s1\" kvg:type=\"\u31d2\" d=\"M26.76,10.25c0.04,0.56,0.08,1.44-0.08,2.25c-0.95,4.74-6.43,15.13-13.93,21.5\"/>\n\t\t\t<path id=\"kvg:07c13-s2\" kvg:type=\"\u31d0b\" d=\"M25.98,21.98c4.36,0,18.37-1.93,23.27-1.93\"/>\n\t\t\t<path id=\"kvg:07c13-s3\" kvg:type=\"\u31d4/\u31d1\" d=\"M33.5,23.75c2.47,1.98,6.38,8.16,7,11.25\"/>\n\t\t</g>\n\t\t<g id=\"kvg:07c13-g3\" kvg:position=\"right\">\n\t\t\t<path id=\"kvg:07c13-s4\" kvg:type=\"\u31d2\" d=\"M60.75,10.5c0.04,0.54,0.16,1.4-0.08,2.15c-1.81,5.63-6.81,13.67-13.43,20.6\"/>\n\t\t\t<path id=\"kvg:07c13-s5\" kvg:type=\"\u31d0b\" d=\"M61.21,19.75c4.95,0,23.11-3.35,28.67-3.35\"/>\n\t\t\t<path id=\"kvg:07c13-s6\" kvg:type=\"\u31d2/\u31da\" d=\"M74.26,21.5c0.04,0.33,0.07,0.85-0.07,1.32c-0.82,2.79-5.51,8.92-11.94,12.68\"/>\n\t\t</g>\n\t</g>\n\t<g id=\"kvg:07c13-g4\" kvg:element=\"\u5f6b\" kvg:position=\"bottom\">\n\t\t<g id=\"kvg:07c13-g5\" kvg:element=\"\u5468\" kvg:variant=\"true\" kvg:position=\"left\">\n\t\t\t<g id=\"kvg:07c13-g6\" kvg:element=\"\u5182\" kvg:variant=\"true\">\n\t\t\t\t<path id=\"kvg:07c13-s7\" kvg:type=\"\u31d2/\u31d1\" d=\"M22.46,39.11c0.53,0.91,1.22,2.33,1.18,3.95c-0.07,2.51-0.12,4.83-0.43,16.65C22.86,72.94,21.5,87,13.26,95.6\"/>\n\t\t\t\t<path id=\"kvg:07c13-s8\" kvg:type=\"\u31c6a\" d=\"M25.41,42.29c4.03-0.59,26.16-3.57,26.96-3.55c1.49,0.03,2.29,1.65,2.26,3.24c-0.03,1.68-0.78,45.81-0.85,49.68c-0.12,6.05-1.21,6.1-4.51,1.93\"/>\n\t\t\t</g>\n\t\t\t<g id=\"kvg:07c13-g7\" kvg:element=\"\u5409\" kvg:variant=\"true\">\n\t\t\t\t<g id=\"kvg:07c13-g8\" kvg:element=\"\u58eb\" kvg:variant=\"true\">\n\t\t\t\t\t<path id=\"kvg:07c13-s9\" kvg:type=\"\u31d0\" d=\"M29.28,54.3c0.65,0.2,1.83,0.14,2.49,0.12c3.51-0.11,11.13-1.51,13.72-1.6c1.08-0.04,1.73,0.03,2.27,0.13\"/>\n\t\t\t\t\t<path id=\"kvg:07c13-s10\" kvg:type=\"\u31d0\" d=\"M27.96,65.03c0.65,0.08,1.85,0.02,2.5,0.01C36,65,43.44,62.62,47.7,62.49c1.09-0.03,1.74-0.01,2.28,0.02\"/>\n\t\t\t\t\t<path id=\"kvg:07c13-s11\" kvg:type=\"\u31d1\" d=\"M37.29,46.53c0.54,0.18,0.86,0.86,0.97,1.25c0.11,0.39,0.01,18.47-0.1,20.96\"/>\n\t\t\t\t</g>\n\t\t\t\t<g id=\"kvg:07c13-g9\" kvg:element=\"\u53e3\">\n\t\t\t\t\t<path id=\"kvg:07c13-s12\" kvg:type=\"\u31d1\" d=\"M29.02,73.12c0.23,0.21,0.47,0.39,0.57,0.66c0.81,2.13,1.8,9.23,2.36,13.07\"/>\n\t\t\t\t\t<path id=\"kvg:07c13-s13\" kvg:type=\"\u31d5b\" d=\"M30.13,74.75c4.07-0.67,13.63-2.09,15.73-2.2c0.77-0.04,1.17,1.05,1.03,1.6c-0.57,2.28-1.73,5.92-2.87,9.18\"/>\n\t\t\t\t\t<path id=\"kvg:07c13-s14\" kvg:type=\"\u31d0b\" d=\"M32.75,84.74c3.29-0.46,11.03-1.25,13.47-1.32\"/>\n\t\t\t\t</g>\n\t\t\t</g>\n\t\t</g>\n\t\t<g id=\"kvg:07c13-g10\" kvg:element=\"\u5f61\" kvg:position=\"right\">\n\t\t\t<path id=\"kvg:07c13-s15\" kvg:type=\"\u31d2\" d=\"M84.89,33.4c0.07,0.54,0.28,1.48-0.14,2.17c-2.56,4.2-11.25,15.19-24,19.94\"/>\n\t\t\t<path id=\"kvg:07c13-s16\" kvg:type=\"\u31d2\" d=\"M90.25,50.75c0.08,0.54,0.29,1.47-0.16,2.17c-3.1,4.74-14.84,16.33-28.41,20.74\"/>\n\t\t\t<path id=\"kvg:07c13-s17\" kvg:type=\"\u31d2\" d=\"M94.66,67.4c0.13,0.68,0.43,1.79-0.1,2.74C90.94,76.65,78.25,91.5,60.75,97\"/>\n\t\t</g>\n\t</g>\n</g>\n</g>\n<g id=\"kvg:StrokeNumbers_07c13\" style=\"font-size:8;fill:#808080\">\n\t<text transform=\"matrix(1 0 0 1 18.50 10.50)\">1</text>\n\t<text transform=\"matrix(1 0 0 1 32.50 18.50)\">2</text>\n\t<text transform=\"matrix(1 0 0 1 27.50 30.50)\">3</text>\n\t<text transform=\"matrix(1 0 0 1 52.50 10.50)\">4</text>\n\t<text transform=\"matrix(1 0 0 1 66.50 16.50)\">5</text>\n\t<text transform=\"matrix(1 0 0 1 64.50 28.50)\">6</text>\n\t<text transform=\"matrix(1 0 0 1 13.50 44.50)\">7</text>\n\t<text transform=\"matrix(1 0 0 1 25.50 39.50)\">8</text>\n\t<text transform=\"matrix(1 0 0 1 27.50 51.50)\">9</text>\n\t<text transform=\"matrix(1 0 0 1 27.50 62.50)\">10</text>\n\t<text transform=\"matrix(1 0 0 1 41.50 48.50)\">11</text>\n\t<text transform=\"matrix(1 0 0 1 22.50 82.50)\">12</text>\n\t<text transform=\"matrix(1 0 0 1 29.50 72.50)\">13</text>\n\t<text transform=\"matrix(1 0 0 1 33.50 81.50)\">14</text>\n\t<text transform=\"matrix(1 0 0 1 74.50 33.50)\">15</text>\n\t<text transform=\"matrix(1 0 0 1 78.50 52.50)\">16</text>\n\t<text transform=\"matrix(1 0 0 1 84.50 68.50)\">17</text>\n</g>\n</svg>"
}