{
    "kanji": "\u83e0",
    "hexadecimal": "083e0",
    "jpdb_keyword": "",
    "rtk_keyword": "",
    "kklc_keyword": "",
    "frequency": 0,
    "jouyou_level": "",
    "JLPT": "",
    "onyomi": [],
    "kunyomi": [],
    "components": [],
    "strokes": 0,
    "svg": "b'<?xml version=\"1.0\" encoding=\"UTF-8\"?>\\n<!--\\nCopyright (C) 2009/2010/2011 Ulrich Apel.\\nThis work is distributed under the conditions of the Creative Commons\\nAttribution-Share Alike 3.0 Licence. This means you are free:\\n* to Share - to copy, distribute and transmit the work\\n* to Remix - to adapt the work\\n\\nUnder the following conditions:\\n* Attribution. You must attribute the work by stating your use of KanjiVG in\\n  your own copyright header and linking to KanjiVG\\'s website\\n  (http://kanjivg.tagaini.net)\\n* Share Alike. If you alter, transform, or build upon this work, you may\\n  distribute the resulting work only under the same or similar license to this\\n  one.\\n\\nSee http://creativecommons.org/licenses/by-sa/3.0/ for more details.\\n-->\\n<!DOCTYPE svg PUBLIC \"-//W3C//DTD SVG 1.0//EN\" \"http://www.w3.org/TR/2001/REC-SVG-20010904/DTD/svg10.dtd\" [\\n<!ATTLIST g\\nxmlns:kvg CDATA #FIXED \"http://kanjivg.tagaini.net\"\\nkvg:element CDATA #IMPLIED\\nkvg:variant CDATA #IMPLIED\\nkvg:partial CDATA #IMPLIED\\nkvg:original CDATA #IMPLIED\\nkvg:part CDATA #IMPLIED\\nkvg:number CDATA #IMPLIED\\nkvg:tradForm CDATA #IMPLIED\\nkvg:radicalForm CDATA #IMPLIED\\nkvg:position CDATA #IMPLIED\\nkvg:radical CDATA #IMPLIED\\nkvg:phon CDATA #IMPLIED >\\n<!ATTLIST path\\nxmlns:kvg CDATA #FIXED \"http://kanjivg.tagaini.net\"\\nkvg:type CDATA #IMPLIED >\\n]>\\n<svg xmlns=\"http://www.w3.org/2000/svg\" width=\"109\" height=\"109\" viewBox=\"0 0 109 109\">\\n<g id=\"kvg:StrokePaths_083e0\" style=\"fill:none;stroke:#000000;stroke-width:3;stroke-linecap:round;stroke-linejoin:round;\">\\n<g id=\"kvg:083e0\" kvg:element=\"\\xe8\\x8f\\xa0\">\\n\\t<g id=\"kvg:083e0-g1\" kvg:element=\"\\xe8\\x89\\xb9\" kvg:variant=\"true\" kvg:original=\"\\xe8\\x89\\xb8\" kvg:position=\"top\" kvg:radical=\"general\">\\n\\t\\t<path id=\"kvg:083e0-s1\" kvg:type=\"\\xe3\\x87\\x90\" d=\"M15.83,23.83c1.29,0.53,7.04,0.27,8.33,0.17c11.9-0.96,48.11-4.43,61.83-4.5c2.16-0.01,6.26,0.57,7.33,0.83\"/>\\n\\t\\t<path id=\"kvg:083e0-s2\" kvg:type=\"\\xe3\\x87\\x91a\" d=\"M35.17,12c2.33,0.5,2.82,2.15,3,3c1.69,7.99,2.08,13.5,2.33,18.17\"/>\\n\\t\\t<path id=\"kvg:083e0-s3\" kvg:type=\"\\xe3\\x87\\x91a\" d=\"M67.83,10.5c1.32,0.89,1.35,3.13,1.04,4.49C67.75,20,67.5,22,65.27,29.33\"/>\\n\\t</g>\\n\\t<g id=\"kvg:083e0-g2\" kvg:element=\"\\xe6\\xb3\\xa2\" kvg:position=\"bottom\">\\n\\t\\t<g id=\"kvg:083e0-g3\" kvg:element=\"\\xe6\\xb0\\xb5\" kvg:variant=\"true\" kvg:original=\"\\xe6\\xb0\\xb4\" kvg:position=\"left\">\\n\\t\\t\\t<path id=\"kvg:083e0-s4\" kvg:type=\"\\xe3\\x87\\x94\" d=\"M21.93,35.69c3.89,1.68,10.04,5.78,11.01,8.39\"/>\\n\\t\\t\\t<path id=\"kvg:083e0-s5\" kvg:type=\"\\xe3\\x87\\x94\" d=\"M16.3,55.82c4.09,1.2,10.57,5.46,11.59,7.32\"/>\\n\\t\\t\\t<path id=\"kvg:083e0-s6\" kvg:type=\"\\xe3\\x87\\x80\" d=\"M15.75,94.74c2.75,0.76,3.33,0.75,4.92-1.57c4.63-6.77,10.99-16.33,15.2-24.96\"/>\\n\\t\\t</g>\\n\\t\\t<g id=\"kvg:083e0-g4\" kvg:element=\"\\xe7\\x9a\\xae\" kvg:position=\"right\">\\n\\t\\t\\t<path id=\"kvg:083e0-s7\" kvg:type=\"\\xe3\\x87\\x92\" d=\"M45.33,46c0.6,0.98,0.82,2.46,0.83,4.5c0.19,24.53-4.92,36.75-12.2,47.36\"/>\\n\\t\\t\\t<path id=\"kvg:083e0-s8\" kvg:type=\"\\xe3\\x87\\x96b\" d=\"M46.83,47c11.67-2,31.21-3.95,36.6-4.04c9.17-0.16,6.75,3.44,1.24,7.54\"/>\\n\\t\\t\\t<path id=\"kvg:083e0-s9\" kvg:type=\"\\xe3\\x87\\x91a\" d=\"M63.67,33.83c0.93,0.34,1.83,2.67,1.83,4.33c0,0.71-0.08,16.26-0.08,23.23\"/>\\n\\t\\t\\t<path id=\"kvg:083e0-s10\" kvg:type=\"\\xe3\\x87\\x87\" d=\"M49.17,64.17c1.27,0.37,2.08,0.39,4.67,0c3.81-0.58,21.85-3.11,23.67-3.5c4.55-0.97,5,1.08,3.04,4.58c-7.93,14.15-25.04,29-41.37,34.75\"/>\\n\\t\\t\\t<path id=\"kvg:083e0-s11\" kvg:type=\"\\xe3\\x87\\x8f\" d=\"M53.98,68.4c3.32,0.77,19.52,19.85,32.19,27.1c1.93,1.11,5.19,2,6.86,2.43\"/>\\n\\t\\t</g>\\n\\t</g>\\n</g>\\n</g>\\n<g id=\"kvg:StrokeNumbers_083e0\" style=\"font-size:8;fill:#808080\">\\n\\t<text transform=\"matrix(1 0 0 1 8.50 23.50)\">1</text>\\n\\t<text transform=\"matrix(1 0 0 1 26.50 12.50)\">2</text>\\n\\t<text transform=\"matrix(1 0 0 1 58.50 10.50)\">3</text>\\n\\t<text transform=\"matrix(1 0 0 1 13.50 35.50)\">4</text>\\n\\t<text transform=\"matrix(1 0 0 1 8.50 56.50)\">5</text>\\n\\t<text transform=\"matrix(1 0 0 1 8.50 97.50)\">6</text>\\n\\t<text transform=\"matrix(1 0 0 1 38.50 53.50)\">7</text>\\n\\t<text transform=\"matrix(1 0 0 1 47.50 43.50)\">8</text>\\n\\t<text transform=\"matrix(1 0 0 1 55.50 34.50)\">9</text>\\n\\t<text transform=\"matrix(1 0 0 1 49.50 61.50)\">10</text>\\n\\t<text transform=\"matrix(1 0 0 1 48.50 76.50)\">11</text>\\n</g>\\n</svg>\\n'"
}