{
    "kanji": "\u8420",
    "hexadecimal": "08420",
    "jpdb_keyword": "",
    "rtk_keyword": "",
    "kklc_keyword": "",
    "frequency": 0,
    "jouyou_level": "",
    "JLPT": "",
    "onyomi": [],
    "kunyomi": [],
    "components": [],
    "strokes": 0,
    "svg": "b'<?xml version=\"1.0\" encoding=\"UTF-8\"?>\\n<!--\\nCopyright (C) 2009/2010/2011 Ulrich Apel.\\nThis work is distributed under the conditions of the Creative Commons\\nAttribution-Share Alike 3.0 Licence. This means you are free:\\n* to Share - to copy, distribute and transmit the work\\n* to Remix - to adapt the work\\n\\nUnder the following conditions:\\n* Attribution. You must attribute the work by stating your use of KanjiVG in\\n  your own copyright header and linking to KanjiVG\\'s website\\n  (http://kanjivg.tagaini.net)\\n* Share Alike. If you alter, transform, or build upon this work, you may\\n  distribute the resulting work only under the same or similar license to this\\n  one.\\n\\nSee http://creativecommons.org/licenses/by-sa/3.0/ for more details.\\n-->\\n<!DOCTYPE svg PUBLIC \"-//W3C//DTD SVG 1.0//EN\" \"http://www.w3.org/TR/2001/REC-SVG-20010904/DTD/svg10.dtd\" [\\n<!ATTLIST g\\nxmlns:kvg CDATA #FIXED \"http://kanjivg.tagaini.net\"\\nkvg:element CDATA #IMPLIED\\nkvg:variant CDATA #IMPLIED\\nkvg:partial CDATA #IMPLIED\\nkvg:original CDATA #IMPLIED\\nkvg:part CDATA #IMPLIED\\nkvg:number CDATA #IMPLIED\\nkvg:tradForm CDATA #IMPLIED\\nkvg:radicalForm CDATA #IMPLIED\\nkvg:position CDATA #IMPLIED\\nkvg:radical CDATA #IMPLIED\\nkvg:phon CDATA #IMPLIED >\\n<!ATTLIST path\\nxmlns:kvg CDATA #FIXED \"http://kanjivg.tagaini.net\"\\nkvg:type CDATA #IMPLIED >\\n]>\\n<svg xmlns=\"http://www.w3.org/2000/svg\" width=\"109\" height=\"109\" viewBox=\"0 0 109 109\">\\n<g id=\"kvg:StrokePaths_08420\" style=\"fill:none;stroke:#000000;stroke-width:3;stroke-linecap:round;stroke-linejoin:round;\">\\n<g id=\"kvg:08420\" kvg:element=\"\\xe8\\x90\\xa0\">\\n\\t<g id=\"kvg:08420-g1\" kvg:element=\"\\xe8\\x89\\xb9\" kvg:variant=\"true\" kvg:original=\"\\xe8\\x89\\xb8\" kvg:position=\"top\" kvg:radical=\"general\">\\n\\t\\t<path id=\"kvg:08420-s1\" kvg:type=\"\\xe3\\x87\\x90\" d=\"M16.17,26.5c1.38,0.68,4.83,1.5,7.67,1.17C36.45,26.18,68.75,23,85,22.5c3.26-0.1,7.35,0.66,8.5,1\"/>\\n\\t\\t<path id=\"kvg:08420-s2\" kvg:type=\"\\xe3\\x87\\x91a\" d=\"M37.17,14.67c2.17,0.5,3.29,1.99,3.5,2.83c1.97,7.87,2.1,14.31,2.67,17.17\"/>\\n\\t\\t<path id=\"kvg:08420-s3\" kvg:type=\"\\xe3\\x87\\x91a\" d=\"M64,11.5c1.67,0.67,2.39,2.44,2.33,4c-0.17,4.5-1.05,12.65-2.17,18.67\"/>\\n\\t</g>\\n\\t<g id=\"kvg:08420-g2\" kvg:element=\"\\xe6\\x9c\\x8b\" kvg:variant=\"true\" kvg:position=\"bottom\">\\n\\t\\t<g id=\"kvg:08420-g3\" kvg:element=\"\\xe6\\x9c\\x88\" kvg:variant=\"true\" kvg:position=\"left\">\\n\\t\\t\\t<path id=\"kvg:08420-s4\" kvg:type=\"\\xe3\\x87\\x93\" d=\"M23.67,40.17c1.08,0.58,1.99,2.53,2,3.33c0.08,7.25,0.06,8.5,0.06,15.9c0,12.87-3.06,30.41-10.54,38.44\"/>\\n\\t\\t\\t<path id=\"kvg:08420-s5\" kvg:type=\"\\xe3\\x87\\x86\" d=\"M26.21,42.45c3.18-0.19,16.43-2.73,18.79-2.95c4.24-0.39,4.27,2,4.27,3.23c0,6.59-0.21,32.76-0.21,47.22c0,10.08-5.24,3.8-7.89,2.05\"/>\\n\\t\\t\\t<path id=\"kvg:08420-s6\" kvg:type=\"\\xe3\\x87\\x94\" d=\"M31.77,49.92c3.19,1.58,8.24,6.51,9.04,8.97\"/>\\n\\t\\t\\t<path id=\"kvg:08420-s7\" kvg:type=\"\\xe3\\x87\\x94\" d=\"M30.77,68.08c3.63,1.74,9.38,7.17,10.29,9.88\"/>\\n\\t\\t</g>\\n\\t\\t<g id=\"kvg:08420-g4\" kvg:element=\"\\xe6\\x9c\\x88\" kvg:variant=\"true\" kvg:position=\"right\">\\n\\t\\t\\t<path id=\"kvg:08420-s8\" kvg:type=\"\\xe3\\x87\\x93\" d=\"M60.5,38.33c0.75,0.92,1.83,2.37,1.83,3.17c0,3.58,0.26,14.43,0.26,19.56c0,13.8-2.19,29.18-6.98,34.69\"/>\\n\\t\\t\\t<path id=\"kvg:08420-s9\" kvg:type=\"\\xe3\\x87\\x86\" d=\"M63,39.83c4.25-0.58,19.71-3.13,21.51-3.35c3.22-0.39,3.22,1.7,3.22,2.94c0,6.66-0.6,35.68-0.6,50.29c0,15.28-6.44,4.38-8.46,2.62\"/>\\n\\t\\t\\t<path id=\"kvg:08420-s10\" kvg:type=\"\\xe3\\x87\\x94\" d=\"M69.02,46.75c3.63,1.86,9.38,7.65,10.29,10.55\"/>\\n\\t\\t\\t<path id=\"kvg:08420-s11\" kvg:type=\"\\xe3\\x87\\x94\" d=\"M68.43,64.92c3.6,1.77,9.31,7.29,10.21,10.05\"/>\\n\\t\\t</g>\\n\\t</g>\\n</g>\\n</g>\\n<g id=\"kvg:StrokeNumbers_08420\" style=\"font-size:8;fill:#808080\">\\n\\t<text transform=\"matrix(1 0 0 1 9.50 27.50)\">1</text>\\n\\t<text transform=\"matrix(1 0 0 1 29.50 14.50)\">2</text>\\n\\t<text transform=\"matrix(1 0 0 1 55.50 12.50)\">3</text>\\n\\t<text transform=\"matrix(1 0 0 1 16.50 47.50)\">4</text>\\n\\t<text transform=\"matrix(1 0 0 1 28.25 38.50)\">5</text>\\n\\t<text transform=\"matrix(1 0 0 1 34.50 48.50)\">6</text>\\n\\t<text transform=\"matrix(1 0 0 1 30.50 65.50)\">7</text>\\n\\t<text transform=\"matrix(1 0 0 1 54.50 47.50)\">8</text>\\n\\t<text transform=\"matrix(1 0 0 1 68.50 35.50)\">9</text>\\n\\t<text transform=\"matrix(1 0 0 1 71.50 46.50)\">10</text>\\n\\t<text transform=\"matrix(1 0 0 1 67.50 62.50)\">11</text>\\n</g>\\n</svg>\\n'"
}